Workbook

Sheet README
A1: Base de datos de nomina para Java
A3: Este archivo .xlsx funciona como catalogo y plantilla de calculo.
A4: Puedes usarlo como base de datos para tu programa en Java y tambien como hoja de prueba para calcular la nomina.
A6: Flujo recomendado
A7: 1) Captura o importa puestos, plazas, empleados, conceptos y deducciones en sus hojas.
A8: 2) Registra incidencias del periodo en la hoja Movimientos.
A9: 3) Define el periodo a calcular en Configuracion!B2 con formato YYYY-MM.
A10: 4) Revisa Calculo_Individual para un empleado o Nomina_General para todos.
A11: 5) Si tu programa Java lee este archivo, usa los encabezados de la fila 1 como nombres de campo estables.
A13: Hojas incluidas
A14: hoja | B14: uso_principal | C14: editable | D14: comentario
A15: Configuracion | B15: Periodo activo y parametros generales | C15: SI | D15: B2 controla el periodo del calculo
A16: Puestos | B16: Catalogo de puestos y sueldos base | C16: SI | D16: El sueldo cambia segun el puesto
A17: Plazas | B17: Catalogo de plazas/departamentos | C17: SI | D17: Sirve para clasificar al personal
A18: Conceptos_Pago | B18: Catalogo de percepciones | C18: SI | D18: Incluye fijos y variables
A19: Deducciones | B19: Catalogo de deducciones | C19: SI | D19: Acepta montos fijos o porcentajes
A20: Empleados | B20: Catalogo de empleados | C20: SI | D20: Incluye formulas auxiliares
A21: Movimientos | B21: Incidencias por periodo | C21: SI | D21: Aqui van bonos, horas extra y descuentos
A22: Calculo_Individual | B22: Nomina de un empleado | C22: SI | D22: Selecciona empleado y periodo
A23: Nomina_General | B23: Nomina de todos | C23: SI | D23: Calcula a todos al mismo tiempo

Sheet Configuracion
A1: parametro | B1: valor | C1: comentario
A2: periodo_nomina | B2: 2026-03 | C2: Periodo base para Calculo_Individual y Nomina_General. Formato YYYY-MM
A3: moneda | B3: MXN | C3: Moneda de trabajo
A4: version_plantilla | B4: 1.0 | C4: Control de version de la estructura
A5: max_empleados_calculo | B5: 200 | C5: Filas precargadas en Nomina_General

Sheet Puestos
A1: puesto | B1: sueldo_base | C1: sueldo_base_mensual | D1: bono_fijo_mensual | E1: pago_hora_extra | F1: activo
A2: P001 | B2: Auxiliar Administrativo | C2: 12000 | D2: 1000 | E2: 90 | F2: SI
A3: P002 | B3: Analista | C3: 18000 | D3: 1500 | E3: 120 | F3: SI
A4: P003 | B4: Supervisor | C4: 25000 | D4: 3000 | E4: 160 | F4: SI
A5: P004 | B5: Gerente | C5: 35000 | D5: 5000 | E5: 220 | F5: SI
A102: administrador | B102: 20000

Sheet Plazas
A1: id_plaza | B1: plaza | C1: departamento | D1: tipo_plaza | E1: centro_costos | F1: horas_semana | G1: activo
A2: PL001 | B2: Administracion General | C2: Administracion | D2: Base | E2: CC-100 | F2: 40 | G2: SI
A3: PL002 | B3: Analisis de Datos | C3: Tecnologia | D3: Base | E3: CC-200 | F3: 40 | G3: SI
A4: PL003 | B4: Operacion Campo | C4: Operaciones | D4: Operativa | E4: CC-300 | F4: 48 | G4: SI
A5: PL004 | B5: Direccion | C5: Direccion | D5: Confianza | E5: CC-400 | F5: 45 | G5: SI

Sheet Conceptos_Pago
A1: id_concepto_pago | B1: descripcion | C1: tipo | D1: aplica_a_todos | E1: monto_default | F1: gravable
A2: CP001 | B2: Vale de despensa | C2: FIJO | D2: SI | E2: 1000 | F2: NO
A3: CP002 | B3: Bono de transporte | C3: FIJO | D3: SI | E3: 500 | F3: SI
A4: CP003 | B4: Bono por productividad | C4: VARIABLE | D4: NO | E4: 0 | F4: SI
A5: CP004 | B5: Horas extra | C5: VARIABLE | D5: NO | E5: 0 | F5: SI

Sheet Deducciones
A1: id_deduccion | B1: descripcion | C1: tipo | D1: base | E1: valor | F1: aplica_a_todos | G1: activo
A2: D001 | B2: ISR general | C2: PORCENTAJE | D2: TOTAL_PERCEPCIONES | E2: 0.1 | F2: SI | G2: SI
A3: D002 | B3: IMSS aproximado | C3: PORCENTAJE | D3: SUELDO_BASE | E3: 0.025 | F3: SI | G3: SI
A4: D003 | B4: Prestamo empresa | C4: FIJO | D4: SUELDO_BASE | E4: 0 | F4: NO | G4: SI

Sheet Empleados
A1: id | B1: nombre | C1: plaza | D1: puesto | E1: sueldo_base | F1: pension | G1: porcentaje_pension | H1: activo | I1: curp | J1: rfc | K1: apellido_paterno | L1: apellido_materno | M1: genero | N1: fecha_nacimiento | O1: calle | P1: numero | Q1: colonia | R1: municipio | S1: estado | T1: telefono | U1: email
A2: E001 | B2: Ana | C2: Lopez | D2: Ramirez | E2: =IF(A2="","",TRIM(B2&" "&C2&" "&D2)) -> Ana Lopez Ramirez | F2: P001 | G2: PL001 | H2: 0 | I2: 2024-01-15 | J2: ACTIVO | K2: 0123456789 | L2: ana@empresa.com | M2: =IF(A2="","",IF(H2>0,H2,IFERROR(INDEX(Puestos!$C$2:$C$100,MATCH(F2,Puestos!$A$2:$A$100,0)),0))) -> 12000 | N2: =IF(A2="","",IFERROR(INDEX(Puestos!$D$2:$D$100,MATCH(F2,Puestos!$A$2:$A$100,0)),0)) -> 1000 | O2: =IF(A2="","",IFERROR(INDEX(Puestos!$B$2:$B$100,MATCH(F2,Puestos!$A$2:$A$100,0)),"")) -> Auxiliar Administrativo | P2: =IF(A2="","",IFERROR(INDEX(Plazas!$B$2:$B$100,MATCH(G2,Plazas!$A$2:$A$100,0)),"")) -> Administracion General
A3: E002 | B3: Luis | C3: Martinez | D3: Gomez | E3: =IF(A3="","",TRIM(B3&" "&C3&" "&D3)) -> Luis Martinez Gomez | F3: P002 | G3: PL002 | H3: 0 | I3: 2023-07-10 | J3: ACTIVO | K3: 0123456790 | L3: luis@empresa.com | M3: =IF(A3="","",IF(H3>0,H3,IFERROR(INDEX(Puestos!$C$2:$C$100,MATCH(F3,Puestos!$A$2:$A$100,0)),0))) -> 18000 | N3: =IF(A3="","",IFERROR(INDEX(Puestos!$D$2:$D$100,MATCH(F3,Puestos!$A$2:$A$100,0)),0)) -> 1500 | O3: =IF(A3="","",IFERROR(INDEX(Puestos!$B$2:$B$100,MATCH(F3,Puestos!$A$2:$A$100,0)),"")) -> Analista | P3: =IF(A3="","",IFERROR(INDEX(Plazas!$B$2:$B$100,MATCH(G3,Plazas!$A$2:$A$100,0)),"")) -> Analisis de Datos
A4: E003 | B4: Sofia | C4: Hernandez | D4: Perez | E4: =IF(A4="","",TRIM(B4&" "&C4&" "&D4)) -> Sofia Hernandez Perez | F4: P003 | G4: PL003 | H4: 28000 | I4: 2022-11-05 | J4: ACTIVO | K4: 0123456791 | L4: sofia@empresa.com | M4: =IF(A4="","",IF(H4>0,H4,IFERROR(INDEX(Puestos!$C$2:$C$100,MATCH(F4,Puestos!$A$2:$A$100,0)),0))) -> 28000 | N4: =IF(A4="","",IFERROR(INDEX(Puestos!$D$2:$D$100,MATCH(F4,Puestos!$A$2:$A$100,0)),0)) -> 3000 | O4: =IF(A4="","",IFERROR(INDEX(Puestos!$B$2:$B$100,MATCH(F4,Puestos!$A$2:$A$100,0)),"")) -> Supervisor | P4: =IF(A4="","",IFERROR(INDEX(Plazas!$B$2:$B$100,MATCH(G4,Plazas!$A$2:$A$100,0)),"")) -> Operacion Campo
A5: E004 | B5: Carlos | C5: Diaz | D5: P001 | E5: 0 | F5: FALSE | G5: 5 | H5: TRUE | I5: 2021-03-01 | J5: INACTIVO | K5: 0123456792 | L5: carlos@empresa.com | M5: masculino | N5: 31/04/08 | O5: privada | P5: 25 | Q5: san javier | R5: xoxocotlan | S5: soltero | T5: 951266644 | U5: carlos@gmail.com
E6: =IF(A6="","",TRIM(B6&" "&C6&" "&D6)) | M6: =IF(A6="","",IF(H6>0,H6,IFERROR(INDEX(Puestos!$C$2:$C$100,MATCH(F6,Puestos!$A$2:$A$100,0)),0))) | N6: =IF(A6="","",IFERROR(INDEX(Puestos!$D$2:$D$100,MATCH(F6,Puestos!$A$2:$A$100,0)),0)) | O6: =IF(A6="","",IFERROR(INDEX(Puestos!$B$2:$B$100,MATCH(F6,Puestos!$A$2:$A$100,0)),"")) | P6: =IF(A6="","",IFERROR(INDEX(Plazas!$B$2:$B$100,MATCH(G6,Plazas!$A$2:$A$100,0)),""))
E7: =IF(A7="","",TRIM(B7&" "&C7&" "&D7)) | M7: =IF(A7="","",IF(H7>0,H7,IFERROR(INDEX(Puestos!$C$2:$C$100,MATCH(F7,Puestos!$A$2:$A$100,0)),0))) | N7: =IF(A7="","",IFERROR(INDEX(Puestos!$D$2:$D$100,MATCH(F7,Puestos!$A$2:$A$100,0)),0)) | O7: =IF(A7="","",IFERROR(INDEX(Puestos!$B$2:$B$100,MATCH(F7,Puestos!$A$2:$A$100,0)),"")) | P7: =IF(A7="","",IFERROR(INDEX(Plazas!$B$2:$B$100,MATCH(G7,Plazas!$A$2:$A$100,0)),""))
E8: =IF(A8="","",TRIM(B8&" "&C8&" "&D8)) | M8: =IF(A8="","",IF(H8>0,H8,IFERROR(INDEX(Puestos!$C$2:$C$100,MATCH(F8,Puestos!$A$2:$A$100,0)),0))) | N8: =IF(A8="","",IFERROR(INDEX(Puestos!$D$2:$D$100,MATCH(F8,Puestos!$A$2:$A$100,0)),0)) | O8: =IF(A8="","",IFERROR(INDEX(Puestos!$B$2:$B$100,MATCH(F8,Puestos!$A$2:$A$100,0)),"")) | P8: =IF(A8="","",IFERROR(INDEX(Plazas!$B$2:$B$100,MATCH(G8,Plazas!$A$2:$A$100,0)),""))
E9: =IF(A9="","",TRIM(B9&" "&C9&" "&D9)) | M9: =IF(A9="","",IF(H9>0,H9,IFERROR(INDEX(Puestos!$C$2:$C$100,MATCH(F9,Puestos!$A$2:$A$100,0)),0))) | N9: =IF(A9="","",IFERROR(INDEX(Puestos!$D$2:$D$100,MATCH(F9,Puestos!$A$2:$A$100,0)),0)) | O9: =IF(A9="","",IFERROR(INDEX(Puestos!$B$2:$B$100,MATCH(F9,Puestos!$A$2:$A$100,0)),"")) | P9: =IF(A9="","",IFERROR(INDEX(Plazas!$B$2:$B$100,MATCH(G9,Plazas!$A$2:$A$100,0)),""))
E10: =IF(A10="","",TRIM(B10&" "&C10&" "&D10)) | M10: =IF(A10="","",IF(H10>0,H10,IFERROR(INDEX(Puestos!$C$2:$C$100,MATCH(F10,Puestos!$A$2:$A$100,0)),0))) | N10: =IF(A10="","",IFERROR(INDEX(Puestos!$D$2:$D$100,MATCH(F10,Puestos!$A$2:$A$100,0)),0)) | O10: =IF(A10="","",IFERROR(INDEX(Puestos!$B$2:$B$100,MATCH(F10,Puestos!$A$2:$A$100,0)),"")) | P10: =IF(A10="","",IFERROR(INDEX(Plazas!$B$2:$B$100,MATCH(G10,Plazas!$A$2:$A$100,0)),""))
E11: =IF(A11="","",TRIM(B11&" "&C11&" "&D11)) | M11: =IF(A11="","",IF(H11>0,H11,IFERROR(INDEX(Puestos!$C$2:$C$100,MATCH(F11,Puestos!$A$2:$A$100,0)),0))) | N11: =IF(A11="","",IFERROR(INDEX(Puestos!$D$2:$D$100,MATCH(F11,Puestos!$A$2:$A$100,0)),0)) | O11: =IF(A11="","",IFERROR(INDEX(Puestos!$B$2:$B$100,MATCH(F11,Puestos!$A$2:$A$100,0)),"")) | P11: =IF(A11="","",IFERROR(INDEX(Plazas!$B$2:$B$100,MATCH(G11,Plazas!$A$2:$A$100,0)),""))
E12: =IF(A12="","",TRIM(B12&" "&C12&" "&D12)) | M12: =IF(A12="","",IF(H12>0,H12,IFERROR(INDEX(Puestos!$C$2:$C$100,MATCH(F12,Puestos!$A$2:$A$100,0)),0))) | N12: =IF(A12="","",IFERROR(INDEX(Puestos!$D$2:$D$100,MATCH(F12,Puestos!$A$2:$A$100,0)),0)) | O12: =IF(A12="","",IFERROR(INDEX(Puestos!$B$2:$B$100,MATCH(F12,Puestos!$A$2:$A$100,0)),"")) | P12: =IF(A12="","",IFERROR(INDEX(Plazas!$B$2:$B$100,MATCH(G12,Plazas!$A$2:$A$100,0)),""))
E13: =IF(A13="","",TRIM(B13&" "&C13&" "&D13)) | M13: =IF(A13="","",IF(H13>0,H13,IFERROR(INDEX(Puestos!$C$2:$C$100,MATCH(F13,Puestos!$A$2:$A$100,0)),0))) | N13: =IF(A13="","",IFERROR(INDEX(Puestos!$D$2:$D$100,MATCH(F13,Puestos!$A$2:$A$100,0)),0)) | O13: =IF(A13="","",IFERROR(INDEX(Puestos!$B$2:$B$100,MATCH(F13,Puestos!$A$2:$A$100,0)),"")) | P13: =IF(A13="","",IFERROR(INDEX(Plazas!$B$2:$B$100,MATCH(G13,Plazas!$A$2:$A$100,0)),""))
E14: =IF(A14="","",TRIM(B14&" "&C14&" "&D14)) | M14: =IF(A14="","",IF(H14>0,H14,IFERROR(INDEX(Puestos!$C$2:$C$100,MATCH(F14,Puestos!$A$2:$A$100,0)),0))) | N14: =IF(A14="","",IFERROR(INDEX(Puestos!$D$2:$D$100,MATCH(F14,Puestos!$A$2:$A$100,0)),0)) | O14: =IF(A14="","",IFERROR(INDEX(Puestos!$B$2:$B$100,MATCH(F14,Puestos!$A$2:$A$100,0)),"")) | P14: =IF(A14="","",IFERROR(INDEX(Plazas!$B$2:$B$100,MATCH(G14,Plazas!$A$2:$A$100,0)),""))
E15: =IF(A15="","",TRIM(B15&" "&C15&" "&D15)) | M15: =IF(A15="","",IF(H15>0,H15,IFERROR(INDEX(Puestos!$C$2:$C$100,MATCH(F15,Puestos!$A$2:$A$100,0)),0))) | N15: =IF(A15="","",IFERROR(INDEX(Puestos!$D$2:$D$100,MATCH(F15,Puestos!$A$2:$A$100,0)),0)) | O15: =IF(A15="","",IFERROR(INDEX(Puestos!$B$2:$B$100,MATCH(F15,Puestos!$A$2:$A$100,0)),"")) | P15: =IF(A15="","",IFERROR(INDEX(Plazas!$B$2:$B$100,MATCH(G15,Plazas!$A$2:$A$100,0)),""))
E16: =IF(A16="","",TRIM(B16&" "&C16&" "&D16)) | M16: =IF(A16="","",IF(H16>0,H16,IFERROR(INDEX(Puestos!$C$2:$C$100,MATCH(F16,Puestos!$A$2:$A$100,0)),0))) | N16: =IF(A16="","",IFERROR(INDEX(Puestos!$D$2:$D$100,MATCH(F16,Puestos!$A$2:$A$100,0)),0)) | O16: =IF(A16="","",IFERROR(INDEX(Puestos!$B$2:$B$100,MATCH(F16,Puestos!$A$2:$A$100,0)),"")) | P16: =IF(A16="","",IFERROR(INDEX(Plazas!$B$2:$B$100,MATCH(G16,Plazas!$A$2:$A$100,0)),""))
E17: =IF(A17="","",TRIM(B17&" "&C17&" "&D17)) | M17: =IF(A17="","",IF(H17>0,H17,IFERROR(INDEX(Puestos!$C$2:$C$100,MATCH(F17,Puestos!$A$2:$A$100,0)),0))) | N17: =IF(A17="","",IFERROR(INDEX(Puestos!$D$2:$D$100,MATCH(F17,Puestos!$A$2:$A$100,0)),0)) | O17: =IF(A17="","",IFERROR(INDEX(Puestos!$B$2:$B$100,MATCH(F17,Puestos!$A$2:$A$100,0)),"")) | P17: =IF(A17="","",IFERROR(INDEX(Plazas!$B$2:$B$100,MATCH(G17,Plazas!$A$2:$A$100,0)),""))
... E201: =IF(A201="","",TRIM(B201&" "&C201&" "&D201)) | M201: =IF(A201="","",IF(H201>0,H201,IFERROR(INDEX(Puestos!$C$2:$C$100,MATCH(F201,Puestos!$A$2:$A$100,0)),0))) | N201: =IF(A201="","",IFERROR(INDEX(Puestos!$D$2:$D$100,MATCH(F201,Puestos!$A$2:$A$100,0)),0)) | O201: =IF(A201="","",IFERROR(INDEX(Puestos!$B$2:$B$100,MATCH(F201,Puestos!$A$2:$A$100,0)),"")) | P201: =IF(A201="","",IFERROR(INDEX(Plazas!$B$2:$B$100,MATCH(G201,Plazas!$A$2:$A$100,0)),""))

Sheet Movimientos
A1: periodo | B1: id_empleado | C1: tipo_movimiento | D1: clave | E1: descripcion | F1: monto | G1: observaciones
A2: 2026-03 | B2: E001 | C2: PAGO | D2: CP004 | E2: Horas extra | F2: 720 | G2: 8 horas
A3: 2026-03 | B3: E002 | C3: PAGO | D3: CP003 | E3: Bono por productividad | F3: 1500 | G3: Meta cumplida
A4: 2026-03 | B4: E003 | C4: DEDUCCION | D4: D003 | E4: Prestamo empresa | F4: 900 | G4: Descuento mensual
A5: 2026-04 | B5: E001 | C5: PAGO | D5: CP003 | E5: Bono por productividad | F5: 800 | G5: Meta parcial

Sheet Calculo_Individual
A1: Calculo individual de nomina
A2: id_empleado | B2: E001
A3: periodo | B3: =Configuracion!B2 -> 2026-03
A5: nombre_completo | B5: =IFERROR(INDEX(Empleados!$E$2:$E$201,MATCH($B$2,Empleados!$A$2:$A$201,0)),"") -> Ana Lopez Ramirez
A6: puesto | B6: =IFERROR(INDEX(Empleados!$O$2:$O$201,MATCH($B$2,Empleados!$A$2:$A$201,0)),"") -> Auxiliar Administrativo
A7: plaza | B7: =IFERROR(INDEX(Empleados!$P$2:$P$201,MATCH($B$2,Empleados!$A$2:$A$201,0)),"") -> Administracion General
A8: estatus | B8: =IFERROR(INDEX(Empleados!$J$2:$J$201,MATCH($B$2,Empleados!$A$2:$A$201,0)),"") -> ACTIVO
A10: Desglose
A11: sueldo_base | B11: =IF($B$8<>"ACTIVO",0,IFERROR(INDEX(Empleados!$M$2:$M$201,MATCH($B$2,Empleados!$A$2:$A$201,0)),0)) -> 12000
A12: bono_puesto | B12: =IF($B$8<>"ACTIVO",0,IFERROR(INDEX(Empleados!$N$2:$N$201,MATCH($B$2,Empleados!$A$2:$A$201,0)),0)) -> 1000
A13: conceptos_fijos_globales | B13: =IF($B$8<>"ACTIVO",0,SUMIFS(Conceptos_Pago!$E$2:$E$100,Conceptos_Pago!$C$2:$C$100,"FIJO",Conceptos_Pago!$D$2:$D$100,"SI")) -> 1500
A14: percepciones_variables_periodo | B14: =IF($B$8<>"ACTIVO",0,SUMIFS(Movimientos!$F$2:$F$500,Movimientos!$A$2:$A$500,$B$3,Movimientos!$B$2:$B$500,$B$2,Movimientos!$C$2:$C$500,"PAGO")) -> 720
A15: total_percepciones | B15: =SUM(B11:B14) -> 15220
A17: deducciones_globales | B17: =IF($B$8<>"ACTIVO",0,SUMIFS(Deducciones!$E$2:$E$100,Deducciones!$F$2:$F$100,"SI",Deducciones!$G$2:$G$100,"SI",Deducciones!$C$2:$C$100,"FIJO")+B11*SUMIFS(Deducciones!$E$2:$E$100,Deducciones!$F$2:$F$100,"SI",Deducciones!$G$2:$G$100,"SI",Deducciones!$C$2:$C$100,"PORCENTAJE",Deducciones!$D$2:$D$100,"SUELDO_BASE")+B15*SUMIFS(Deducciones!$E$2:$E$100,Deducciones!$F$2:$F$100,"SI",Deducciones!$G$2:$G$100,"SI",Deducciones!$C$2:$C$100,"PORCENTAJE",Deducciones!$D$2:$D$100,"TOTAL_PERCEPCIONES")) -> 1822
A18: deducciones_variables_periodo | B18: =IF($B$8<>"ACTIVO",0,SUMIFS(Movimientos!$F$2:$F$500,Movimientos!$A$2:$A$500,$B$3,Movimientos!$B$2:$B$500,$B$2,Movimientos!$C$2:$C$500,"DEDUCCION")) -> 0
A19: total_deducciones | B19: =SUM(B17:B18) -> 1822
A21: neto_pagar | B21: =B15-B19 -> 13398

Sheet Nomina_General
A1: Nomina general
A2: periodo | B2: =Configuracion!B2 -> 2026-03
A4: id_empleado | B4: nombre_completo | C4: puesto | D4: plaza | E4: sueldo_base | F4: bono_puesto | G4: conceptos_fijos | H4: percepciones_variables | I4: total_percepciones | J4: deducciones_globales | K4: deducciones_variables | L4: total_deducciones | M4: neto_pagar | N4: estatus
A5: =IF(ROW()-4<=COUNTA(Empleados!$A$2:$A$201),INDEX(Empleados!$A$2:$A$201,ROW()-4),"") -> E001 | B5: =IF($A5="","",INDEX(Empleados!$E$2:$E$201,MATCH($A5,Empleados!$A$2:$A$201,0))) -> Ana Lopez Ramirez | C5: =IF($A5="","",INDEX(Empleados!$O$2:$O$201,MATCH($A5,Empleados!$A$2:$A$201,0))) -> Auxiliar Administrativo | D5: =IF($A5="","",INDEX(Empleados!$P$2:$P$201,MATCH($A5,Empleados!$A$2:$A$201,0))) -> Administracion General | E5: =IF($A5="","",IF($N5<>"ACTIVO",0,INDEX(Empleados!$M$2:$M$201,MATCH($A5,Empleados!$A$2:$A$201,0)))) -> 12000 | F5: =IF($A5="","",IF($N5<>"ACTIVO",0,INDEX(Empleados!$N$2:$N$201,MATCH($A5,Empleados!$A$2:$A$201,0)))) -> 1000 | G5: =IF($A5="","",IF($N5<>"ACTIVO",0,SUMIFS(Conceptos_Pago!$E$2:$E$100,Conceptos_Pago!$C$2:$C$100,"FIJO",Conceptos_Pago!$D$2:$D$100,"SI"))) -> 1500 | H5: =IF($A5="","",IF($N5<>"ACTIVO",0,SUMIFS(Movimientos!$F$2:$F$500,Movimientos!$A$2:$A$500,$B$2,Movimientos!$B$2:$B$500,$A5,Movimientos!$C$2:$C$500,"PAGO"))) -> 720 | I5: =IF($A5="","",SUM(E5:H5)) -> 15220 | J5: =IF($A5="","",IF($N5<>"ACTIVO",0,SUMIFS(Deducciones!$E$2:$E$100,Deducciones!$F$2:$F$100,"SI",Deducciones!$G$2:$G$100,"SI",Deducciones!$C$2:$C$100,"FIJO")+E5*SUMIFS(Deducciones!$E$2:$E$100,Deducciones!$F$2:$F$100,"SI",Deducciones!$G$2:$G$100,"SI",Deducciones!$C$2:$C$100,"PORCENTAJE",Deducciones!$D$2:$D$100,"SUELDO_BASE")+I5*SUMIFS(Deducciones!$E$2:$E$100,Deducciones!$F$2:$F$100,"SI",Deducciones!$G$2:$G$100,"SI",Deducciones!$C$2:$C$100,"PORCENTAJE",Deducciones!$D$2:$D$100,"TOTAL_PERCEPCIONES"))) -> 1822 | K5: =IF($A5="","",IF($N5<>"ACTIVO",0,SUMIFS(Movimientos!$F$2:$F$500,Movimientos!$A$2:$A$500,$B$2,Movimientos!$B$2:$B$500,$A5,Movimientos!$C$2:$C$500,"DEDUCCION"))) -> 0 | L5: =IF($A5="","",SUM(J5:K5)) -> 1822 | M5: =IF($A5="","",I5-L5) -> 13398 | N5: =IF($A5="","",INDEX(Empleados!$J$2:$J$201,MATCH($A5,Empleados!$A$2:$A$201,0))) -> ACTIVO
A6: =IF(ROW()-4<=COUNTA(Empleados!$A$2:$A$201),INDEX(Empleados!$A$2:$A$201,ROW()-4),"") -> E002 | B6: =IF($A6="","",INDEX(Empleados!$E$2:$E$201,MATCH($A6,Empleados!$A$2:$A$201,0))) -> Luis Martinez Gomez | C6: =IF($A6="","",INDEX(Empleados!$O$2:$O$201,MATCH($A6,Empleados!$A$2:$A$201,0))) -> Analista | D6: =IF($A6="","",INDEX(Empleados!$P$2:$P$201,MATCH($A6,Empleados!$A$2:$A$201,0))) -> Analisis de Datos | E6: =IF($A6="","",IF($N6<>"ACTIVO",0,INDEX(Empleados!$M$2:$M$201,MATCH($A6,Empleados!$A$2:$A$201,0)))) -> 18000 | F6: =IF($A6="","",IF($N6<>"ACTIVO",0,INDEX(Empleados!$N$2:$N$201,MATCH($A6,Empleados!$A$2:$A$201,0)))) -> 1500 | G6: =IF($A6="","",IF($N6<>"ACTIVO",0,SUMIFS(Conceptos_Pago!$E$2:$E$100,Conceptos_Pago!$C$2:$C$100,"FIJO",Conceptos_Pago!$D$2:$D$100,"SI"))) -> 1500 | H6: =IF($A6="","",IF($N6<>"ACTIVO",0,SUMIFS(Movimientos!$F$2:$F$500,Movimientos!$A$2:$A$500,$B$2,Movimientos!$B$2:$B$500,$A6,Movimientos!$C$2:$C$500,"PAGO"))) -> 1500 | I6: =IF($A6="","",SUM(E6:H6)) -> 22500 | J6: =IF($A6="","",IF($N6<>"ACTIVO",0,SUMIFS(Deducciones!$E$2:$E$100,Deducciones!$F$2:$F$100,"SI",Deducciones!$G$2:$G$100,"SI",Deducciones!$C$2:$C$100,"FIJO")+E6*SUMIFS(Deducciones!$E$2:$E$100,Deducciones!$F$2:$F$100,"SI",Deducciones!$G$2:$G$100,"SI",Deducciones!$C$2:$C$100,"PORCENTAJE",Deducciones!$D$2:$D$100,"SUELDO_BASE")+I6*SUMIFS(Deducciones!$E$2:$E$100,Deducciones!$F$2:$F$100,"SI",Deducciones!$G$2:$G$100,"SI",Deducciones!$C$2:$C$100,"PORCENTAJE",Deducciones!$D$2:$D$100,"TOTAL_PERCEPCIONES"))) -> 2700 | K6: =IF($A6="","",IF($N6<>"ACTIVO",0,SUMIFS(Movimientos!$F$2:$F$500,Movimientos!$A$2:$A$500,$B$2,Movimientos!$B$2:$B$500,$A6,Movimientos!$C$2:$C$500,"DEDUCCION"))) -> 0 | L6: =IF($A6="","",SUM(J6:K6)) -> 2700 | M6: =IF($A6="","",I6-L6) -> 19800 | N6: =IF($A6="","",INDEX(Empleados!$J$2:$J$201,MATCH($A6,Empleados!$A$2:$A$201,0))) -> ACTIVO
A7: =IF(ROW()-4<=COUNTA(Empleados!$A$2:$A$201),INDEX(Empleados!$A$2:$A$201,ROW()-4),"") -> E003 | B7: =IF($A7="","",INDEX(Empleados!$E$2:$E$201,MATCH($A7,Empleados!$A$2:$A$201,0))) -> Sofia Hernandez Perez | C7: =IF($A7="","",INDEX(Empleados!$O$2:$O$201,MATCH($A7,Empleados!$A$2:$A$201,0))) -> Supervisor | D7: =IF($A7="","",INDEX(Empleados!$P$2:$P$201,MATCH($A7,Empleados!$A$2:$A$201,0))) -> Operacion Campo | E7: =IF($A7="","",IF($N7<>"ACTIVO",0,INDEX(Empleados!$M$2:$M$201,MATCH($A7,Empleados!$A$2:$A$201,0)))) -> 28000 | F7: =IF($A7="","",IF($N7<>"ACTIVO",0,INDEX(Empleados!$N$2:$N$201,MATCH($A7,Empleados!$A$2:$A$201,0)))) -> 3000 | G7: =IF($A7="","",IF($N7<>"ACTIVO",0,SUMIFS(Conceptos_Pago!$E$2:$E$100,Conceptos_Pago!$C$2:$C$100,"FIJO",Conceptos_Pago!$D$2:$D$100,"SI"))) -> 1500 | H7: =IF($A7="","",IF($N7<>"ACTIVO",0,SUMIFS(Movimientos!$F$2:$F$500,Movimientos!$A$2:$A$500,$B$2,Movimientos!$B$2:$B$500,$A7,Movimientos!$C$2:$C$500,"PAGO"))) -> 0 | I7: =IF($A7="","",SUM(E7:H7)) -> 32500 | J7: =IF($A7="","",IF($N7<>"ACTIVO",0,SUMIFS(Deducciones!$E$2:$E$100,Deducciones!$F$2:$F$100,"SI",Deducciones!$G$2:$G$100,"SI",Deducciones!$C$2:$C$100,"FIJO")+E7*SUMIFS(Deducciones!$E$2:$E$100,Deducciones!$F$2:$F$100,"SI",Deducciones!$G$2:$G$100,"SI",Deducciones!$C$2:$C$100,"PORCENTAJE",Deducciones!$D$2:$D$100,"SUELDO_BASE")+I7*SUMIFS(Deducciones!$E$2:$E$100,Deducciones!$F$2:$F$100,"SI",Deducciones!$G$2:$G$100,"SI",Deducciones!$C$2:$C$100,"PORCENTAJE",Deducciones!$D$2:$D$100,"TOTAL_PERCEPCIONES"))) -> 3950 | K7: =IF($A7="","",IF($N7<>"ACTIVO",0,SUMIFS(Movimientos!$F$2:$F$500,Movimientos!$A$2:$A$500,$B$2,Movimientos!$B$2:$B$500,$A7,Movimientos!$C$2:$C$500,"DEDUCCION"))) -> 900 | L7: =IF($A7="","",SUM(J7:K7)) -> 4850 | M7: =IF($A7="","",I7-L7) -> 27650 | N7: =IF($A7="","",INDEX(Empleados!$J$2:$J$201,MATCH($A7,Empleados!$A$2:$A$201,0))) -> ACTIVO
A8: =IF(ROW()-4<=COUNTA(Empleados!$A$2:$A$201),INDEX(Empleados!$A$2:$A$201,ROW()-4),"") -> E004 | B8: =IF($A8="","",INDEX(Empleados!$E$2:$E$201,MATCH($A8,Empleados!$A$2:$A$201,0))) -> 0 | C8: =IF($A8="","",INDEX(Empleados!$O$2:$O$201,MATCH($A8,Empleados!$A$2:$A$201,0))) -> privada | D8: =IF($A8="","",INDEX(Empleados!$P$2:$P$201,MATCH($A8,Empleados!$A$2:$A$201,0))) -> 25 | E8: =IF($A8="","",IF($N8<>"ACTIVO",0,INDEX(Empleados!$M$2:$M$201,MATCH($A8,Empleados!$A$2:$A$201,0)))) -> 0 | F8: =IF($A8="","",IF($N8<>"ACTIVO",0,INDEX(Empleados!$N$2:$N$201,MATCH($A8,Empleados!$A$2:$A$201,0)))) -> 0 | G8: =IF($A8="","",IF($N8<>"ACTIVO",0,SUMIFS(Conceptos_Pago!$E$2:$E$100,Conceptos_Pago!$C$2:$C$100,"FIJO",Conceptos_Pago!$D$2:$D$100,"SI"))) -> 0 | H8: =IF($A8="","",IF($N8<>"ACTIVO",0,SUMIFS(Movimientos!$F$2:$F$500,Movimientos!$A$2:$A$500,$B$2,Movimientos!$B$2:$B$500,$A8,Movimientos!$C$2:$C$500,"PAGO"))) -> 0 | I8: =IF($A8="","",SUM(E8:H8)) -> 0 | J8: =IF($A8="","",IF($N8<>"ACTIVO",0,SUMIFS(Deducciones!$E$2:$E$100,Deducciones!$F$2:$F$100,"SI",Deducciones!$G$2:$G$100,"SI",Deducciones!$C$2:$C$100,"FIJO")+E8*SUMIFS(Deducciones!$E$2:$E$100,Deducciones!$F$2:$F$100,"SI",Deducciones!$G$2:$G$100,"SI",Deducciones!$C$2:$C$100,"PORCENTAJE",Deducciones!$D$2:$D$100,"SUELDO_BASE")+I8*SUMIFS(Deducciones!$E$2:$E$100,Deducciones!$F$2:$F$100,"SI",Deducciones!$G$2:$G$100,"SI",Deducciones!$C$2:$C$100,"PORCENTAJE",Deducciones!$D$2:$D$100,"TOTAL_PERCEPCIONES"))) -> 0 | K8: =IF($A8="","",IF($N8<>"ACTIVO",0,SUMIFS(Movimientos!$F$2:$F$500,Movimientos!$A$2:$A$500,$B$2,Movimientos!$B$2:$B$500,$A8,Movimientos!$C$2:$C$500,"DEDUCCION"))) -> 0 | L8: =IF($A8="","",SUM(J8:K8)) -> 0 | M8: =IF($A8="","",I8-L8) -> 0 | N8: =IF($A8="","",INDEX(Empleados!$J$2:$J$201,MATCH($A8,Empleados!$A$2:$A$201,0))) -> INACTIVO
A9: =IF(ROW()-4<=COUNTA(Empleados!$A$2:$A$201),INDEX(Empleados!$A$2:$A$201,ROW()-4),"") | B9: =IF($A9="","",INDEX(Empleados!$E$2:$E$201,MATCH($A9,Empleados!$A$2:$A$201,0))) | C9: =IF($A9="","",INDEX(Empleados!$O$2:$O$201,MATCH($A9,Empleados!$A$2:$A$201,0))) | D9: =IF($A9="","",INDEX(Empleados!$P$2:$P$201,MATCH($A9,Empleados!$A$2:$A$201,0))) | E9: =IF($A9="","",IF($N9<>"ACTIVO",0,INDEX(Empleados!$M$2:$M$201,MATCH($A9,Empleados!$A$2:$A$201,0)))) | F9: =IF($A9="","",IF($N9<>"ACTIVO",0,INDEX(Empleados!$N$2:$N$201,MATCH($A9,Empleados!$A$2:$A$201,0)))) | G9: =IF($A9="","",IF($N9<>"ACTIVO",0,SUMIFS(Conceptos_Pago!$E$2:$E$100,Conceptos_Pago!$C$2:$C$100,"FIJO",Conceptos_Pago!$D$2:$D$100,"SI"))) | H9: =IF($A9="","",IF($N9<>"ACTIVO",0,SUMIFS(Movimientos!$F$2:$F$500,Movimientos!$A$2:$A$500,$B$2,Movimientos!$B$2:$B$500,$A9,Movimientos!$C$2:$C$500,"PAGO"))) | I9: =IF($A9="","",SUM(E9:H9)) | J9: =IF($A9="","",IF($N9<>"ACTIVO",0,SUMIFS(Deducciones!$E$2:$E$100,Deducciones!$F$2:$F$100,"SI",Deducciones!$G$2:$G$100,"SI",Deducciones!$C$2:$C$100,"FIJO")+E9*SUMIFS(Deducciones!$E$2:$E$100,Deducciones!$F$2:$F$100,"SI",Deducciones!$G$2:$G$100,"SI",Deducciones!$C$2:$C$100,"PORCENTAJE",Deducciones!$D$2:$D$100,"SUELDO_BASE")+I9*SUMIFS(Deducciones!$E$2:$E$100,Deducciones!$F$2:$F$100,"SI",Deducciones!$G$2:$G$100,"SI",Deducciones!$C$2:$C$100,"PORCENTAJE",Deducciones!$D$2:$D$100,"TOTAL_PERCEPCIONES"))) | K9: =IF($A9="","",IF($N9<>"ACTIVO",0,SUMIFS(Movimientos!$F$2:$F$500,Movimientos!$A$2:$A$500,$B$2,Movimientos!$B$2:$B$500,$A9,Movimientos!$C$2:$C$500,"DEDUCCION"))) | L9: =IF($A9="","",SUM(J9:K9)) | M9: =IF($A9="","",I9-L9) | N9: =IF($A9="","",INDEX(Empleados!$J$2:$J$201,MATCH($A9,Empleados!$A$2:$A$201,0)))
A10: =IF(ROW()-4<=COUNTA(Empleados!$A$2:$A$201),INDEX(Empleados!$A$2:$A$201,ROW()-4),"") | B10: =IF($A10="","",INDEX(Empleados!$E$2:$E$201,MATCH($A10,Empleados!$A$2:$A$201,0))) | C10: =IF($A10="","",INDEX(Empleados!$O$2:$O$201,MATCH($A10,Empleados!$A$2:$A$201,0))) | D10: =IF($A10="","",INDEX(Empleados!$P$2:$P$201,MATCH($A10,Empleados!$A$2:$A$201,0))) | E10: =IF($A10="","",IF($N10<>"ACTIVO",0,INDEX(Empleados!$M$2:$M$201,MATCH($A10,Empleados!$A$2:$A$201,0)))) | F10: =IF($A10="","",IF($N10<>"ACTIVO",0,INDEX(Empleados!$N$2:$N$201,MATCH($A10,Empleados!$A$2:$A$201,0)))) | G10: =IF($A10="","",IF($N10<>"ACTIVO",0,SUMIFS(Conceptos_Pago!$E$2:$E$100,Conceptos_Pago!$C$2:$C$100,"FIJO",Conceptos_Pago!$D$2:$D$100,"SI"))) | H10: =IF($A10="","",IF($N10<>"ACTIVO",0,SUMIFS(Movimientos!$F$2:$F$500,Movimientos!$A$2:$A$500,$B$2,Movimientos!$B$2:$B$500,$A10,Movimientos!$C$2:$C$500,"PAGO"))) | I10: =IF($A10="","",SUM(E10:H10)) | J10: =IF($A10="","",IF($N10<>"ACTIVO",0,SUMIFS(Deducciones!$E$2:$E$100,Deducciones!$F$2:$F$100,"SI",Deducciones!$G$2:$G$100,"SI",Deducciones!$C$2:$C$100,"FIJO")+E10*SUMIFS(Deducciones!$E$2:$E$100,Deducciones!$F$2:$F$100,"SI",Deducciones!$G$2:$G$100,"SI",Deducciones!$C$2:$C$100,"PORCENTAJE",Deducciones!$D$2:$D$100,"SUELDO_BASE")+I10*SUMIFS(Deducciones!$E$2:$E$100,Deducciones!$F$2:$F$100,"SI",Deducciones!$G$2:$G$100,"SI",Deducciones!$C$2:$C$100,"PORCENTAJE",Deducciones!$D$2:$D$100,"TOTAL_PERCEPCIONES"))) | K10: =IF($A10="","",IF($N10<>"ACTIVO",0,SUMIFS(Movimientos!$F$2:$F$500,Movimientos!$A$2:$A$500,$B$2,Movimientos!$B$2:$B$500,$A10,Movimientos!$C$2:$C$500,"DEDUCCION"))) | L10: =IF($A10="","",SUM(J10:K10)) | M10: =IF($A10="","",I10-L10) | N10: =IF($A10="","",INDEX(Empleados!$J$2:$J$201,MATCH($A10,Empleados!$A$2:$A$201,0)))
A11: =IF(ROW()-4<=COUNTA(Empleados!$A$2:$A$201),INDEX(Empleados!$A$2:$A$201,ROW()-4),"") | B11: =IF($A11="","",INDEX(Empleados!$E$2:$E$201,MATCH($A11,Empleados!$A$2:$A$201,0))) | C11: =IF($A11="","",INDEX(Empleados!$O$2:$O$201,MATCH($A11,Empleados!$A$2:$A$201,0))) | D11: =IF($A11="","",INDEX(Empleados!$P$2:$P$201,MATCH($A11,Empleados!$A$2:$A$201,0))) | E11: =IF($A11="","",IF($N11<>"ACTIVO",0,INDEX(Empleados!$M$2:$M$201,MATCH($A11,Empleados!$A$2:$A$201,0)))) | F11: =IF($A11="","",IF($N11<>"ACTIVO",0,INDEX(Empleados!$N$2:$N$201,MATCH($A11,Empleados!$A$2:$A$201,0)))) | G11: =IF($A11="","",IF($N11<>"ACTIVO",0,SUMIFS(Conceptos_Pago!$E$2:$E$100,Conceptos_Pago!$C$2:$C$100,"FIJO",Conceptos_Pago!$D$2:$D$100,"SI"))) | H11: =IF($A11="","",IF($N11<>"ACTIVO",0,SUMIFS(Movimientos!$F$2:$F$500,Movimientos!$A$2:$A$500,$B$2,Movimientos!$B$2:$B$500,$A11,Movimientos!$C$2:$C$500,"PAGO"))) | I11: =IF($A11="","",SUM(E11:H11)) | J11: =IF($A11="","",IF($N11<>"ACTIVO",0,SUMIFS(Deducciones!$E$2:$E$100,Deducciones!$F$2:$F$100,"SI",Deducciones!$G$2:$G$100,"SI",Deducciones!$C$2:$C$100,"FIJO")+E11*SUMIFS(Deducciones!$E$2:$E$100,Deducciones!$F$2:$F$100,"SI",Deducciones!$G$2:$G$100,"SI",Deducciones!$C$2:$C$100,"PORCENTAJE",Deducciones!$D$2:$D$100,"SUELDO_BASE")+I11*SUMIFS(Deducciones!$E$2:$E$100,Deducciones!$F$2:$F$100,"SI",Deducciones!$G$2:$G$100,"SI",Deducciones!$C$2:$C$100,"PORCENTAJE",Deducciones!$D$2:$D$100,"TOTAL_PERCEPCIONES"))) | K11: =IF($A11="","",IF($N11<>"ACTIVO",0,SUMIFS(Movimientos!$F$2:$F$500,Movimientos!$A$2:$A$500,$B$2,Movimientos!$B$2:$B$500,$A11,Movimientos!$C$2:$C$500,"DEDUCCION"))) | L11: =IF($A11="","",SUM(J11:K11)) | M11: =IF($A11="","",I11-L11) | N11: =IF($A11="","",INDEX(Empleados!$J$2:$J$201,MATCH($A11,Empleados!$A$2:$A$201,0)))
A12: =IF(ROW()-4<=COUNTA(Empleados!$A$2:$A$201),INDEX(Empleados!$A$2:$A$201,ROW()-4),"") | B12: =IF($A12="","",INDEX(Empleados!$E$2:$E$201,MATCH($A12,Empleados!$A$2:$A$201,0))) | C12: =IF($A12="","",INDEX(Empleados!$O$2:$O$201,MATCH($A12,Empleados!$A$2:$A$201,0))) | D12: =IF($A12="","",INDEX(Empleados!$P$2:$P$201,MATCH($A12,Empleados!$A$2:$A$201,0))) | E12: =IF($A12="","",IF($N12<>"ACTIVO",0,INDEX(Empleados!$M$2:$M$201,MATCH($A12,Empleados!$A$2:$A$201,0)))) | F12: =IF($A12="","",IF($N12<>"ACTIVO",0,INDEX(Empleados!$N$2:$N$201,MATCH($A12,Empleados!$A$2:$A$201,0)))) | G12: =IF($A12="","",IF($N12<>"ACTIVO",0,SUMIFS(Conceptos_Pago!$E$2:$E$100,Conceptos_Pago!$C$2:$C$100,"FIJO",Conceptos_Pago!$D$2:$D$100,"SI"))) | H12: =IF($A12="","",IF($N12<>"ACTIVO",0,SUMIFS(Movimientos!$F$2:$F$500,Movimientos!$A$2:$A$500,$B$2,Movimientos!$B$2:$B$500,$A12,Movimientos!$C$2:$C$500,"PAGO"))) | I12: =IF($A12="","",SUM(E12:H12)) | J12: =IF($A12="","",IF($N12<>"ACTIVO",0,SUMIFS(Deducciones!$E$2:$E$100,Deducciones!$F$2:$F$100,"SI",Deducciones!$G$2:$G$100,"SI",Deducciones!$C$2:$C$100,"FIJO")+E12*SUMIFS(Deducciones!$E$2:$E$100,Deducciones!$F$2:$F$100,"SI",Deducciones!$G$2:$G$100,"SI",Deducciones!$C$2:$C$100,"PORCENTAJE",Deducciones!$D$2:$D$100,"SUELDO_BASE")+I12*SUMIFS(Deducciones!$E$2:$E$100,Deducciones!$F$2:$F$100,"SI",Deducciones!$G$2:$G$100,"SI",Deducciones!$C$2:$C$100,"PORCENTAJE",Deducciones!$D$2:$D$100,"TOTAL_PERCEPCIONES"))) | K12: =IF($A12="","",IF($N12<>"ACTIVO",0,SUMIFS(Movimientos!$F$2:$F$500,Movimientos!$A$2:$A$500,$B$2,Movimientos!$B$2:$B$500,$A12,Movimientos!$C$2:$C$500,"DEDUCCION"))) | L12: =IF($A12="","",SUM(J12:K12)) | M12: =IF($A12="","",I12-L12) | N12: =IF($A12="","",INDEX(Empleados!$J$2:$J$201,MATCH($A12,Empleados!$A$2:$A$201,0)))
A13: =IF(ROW()-4<=COUNTA(Empleados!$A$2:$A$201),INDEX(Empleados!$A$2:$A$201,ROW()-4),"") | B13: =IF($A13="","",INDEX(Empleados!$E$2:$E$201,MATCH($A13,Empleados!$A$2:$A$201,0))) | C13: =IF($A13="","",INDEX(Empleados!$O$2:$O$201,MATCH($A13,Empleados!$A$2:$A$201,0))) | D13: =IF($A13="","",INDEX(Empleados!$P$2:$P$201,MATCH($A13,Empleados!$A$2:$A$201,0))) | E13: =IF($A13="","",IF($N13<>"ACTIVO",0,INDEX(Empleados!$M$2:$M$201,MATCH($A13,Empleados!$A$2:$A$201,0)))) | F13: =IF($A13="","",IF($N13<>"ACTIVO",0,INDEX(Empleados!$N$2:$N$201,MATCH($A13,Empleados!$A$2:$A$201,0)))) | G13: =IF($A13="","",IF($N13<>"ACTIVO",0,SUMIFS(Conceptos_Pago!$E$2:$E$100,Conceptos_Pago!$C$2:$C$100,"FIJO",Conceptos_Pago!$D$2:$D$100,"SI"))) | H13: =IF($A13="","",IF($N13<>"ACTIVO",0,SUMIFS(Movimientos!$F$2:$F$500,Movimientos!$A$2:$A$500,$B$2,Movimientos!$B$2:$B$500,$A13,Movimientos!$C$2:$C$500,"PAGO"))) | I13: =IF($A13="","",SUM(E13:H13)) | J13: =IF($A13="","",IF($N13<>"ACTIVO",0,SUMIFS(Deducciones!$E$2:$E$100,Deducciones!$F$2:$F$100,"SI",Deducciones!$G$2:$G$100,"SI",Deducciones!$C$2:$C$100,"FIJO")+E13*SUMIFS(Deducciones!$E$2:$E$100,Deducciones!$F$2:$F$100,"SI",Deducciones!$G$2:$G$100,"SI",Deducciones!$C$2:$C$100,"PORCENTAJE",Deducciones!$D$2:$D$100,"SUELDO_BASE")+I13*SUMIFS(Deducciones!$E$2:$E$100,Deducciones!$F$2:$F$100,"SI",Deducciones!$G$2:$G$100,"SI",Deducciones!$C$2:$C$100,"PORCENTAJE",Deducciones!$D$2:$D$100,"TOTAL_PERCEPCIONES"))) | K13: =IF($A13="","",IF($N13<>"ACTIVO",0,SUMIFS(Movimientos!$F$2:$F$500,Movimientos!$A$2:$A$500,$B$2,Movimientos!$B$2:$B$500,$A13,Movimientos!$C$2:$C$500,"DEDUCCION"))) | L13: =IF($A13="","",SUM(J13:K13)) | M13: =IF($A13="","",I13-L13) | N13: =IF($A13="","",INDEX(Empleados!$J$2:$J$201,MATCH($A13,Empleados!$A$2:$A$201,0)))
A14: =IF(ROW()-4<=COUNTA(Empleados!$A$2:$A$201),INDEX(Empleados!$A$2:$A$201,ROW()-4),"") | B14: =IF($A14="","",INDEX(Empleados!$E$2:$E$201,MATCH($A14,Empleados!$A$2:$A$201,0))) | C14: =IF($A14="","",INDEX(Empleados!$O$2:$O$201,MATCH($A14,Empleados!$A$2:$A$201,0))) | D14: =IF($A14="","",INDEX(Empleados!$P$2:$P$201,MATCH($A14,Empleados!$A$2:$A$201,0))) | E14: =IF($A14="","",IF($N14<>"ACTIVO",0,INDEX(Empleados!$M$2:$M$201,MATCH($A14,Empleados!$A$2:$A$201,0)))) | F14: =IF($A14="","",IF($N14<>"ACTIVO",0,INDEX(Empleados!$N$2:$N$201,MATCH($A14,Empleados!$A$2:$A$201,0)))) | G14: =IF($A14="","",IF($N14<>"ACTIVO",0,SUMIFS(Conceptos_Pago!$E$2:$E$100,Conceptos_Pago!$C$2:$C$100,"FIJO",Conceptos_Pago!$D$2:$D$100,"SI"))) | H14: =IF($A14="","",IF($N14<>"ACTIVO",0,SUMIFS(Movimientos!$F$2:$F$500,Movimientos!$A$2:$A$500,$B$2,Movimientos!$B$2:$B$500,$A14,Movimientos!$C$2:$C$500,"PAGO"))) | I14: =IF($A14="","",SUM(E14:H14)) | J14: =IF($A14="","",IF($N14<>"ACTIVO",0,SUMIFS(Deducciones!$E$2:$E$100,Deducciones!$F$2:$F$100,"SI",Deducciones!$G$2:$G$100,"SI",Deducciones!$C$2:$C$100,"FIJO")+E14*SUMIFS(Deducciones!$E$2:$E$100,Deducciones!$F$2:$F$100,"SI",Deducciones!$G$2:$G$100,"SI",Deducciones!$C$2:$C$100,"PORCENTAJE",Deducciones!$D$2:$D$100,"SUELDO_BASE")+I14*SUMIFS(Deducciones!$E$2:$E$100,Deducciones!$F$2:$F$100,"SI",Deducciones!$G$2:$G$100,"SI",Deducciones!$C$2:$C$100,"PORCENTAJE",Deducciones!$D$2:$D$100,"TOTAL_PERCEPCIONES"))) | K14: =IF($A14="","",IF($N14<>"ACTIVO",0,SUMIFS(Movimientos!$F$2:$F$500,Movimientos!$A$2:$A$500,$B$2,Movimientos!$B$2:$B$500,$A14,Movimientos!$C$2:$C$500,"DEDUCCION"))) | L14: =IF($A14="","",SUM(J14:K14)) | M14: =IF($A14="","",I14-L14) | N14: =IF($A14="","",INDEX(Empleados!$J$2:$J$201,MATCH($A14,Empleados!$A$2:$A$201,0)))
A15: =IF(ROW()-4<=COUNTA(Empleados!$A$2:$A$201),INDEX(Empleados!$A$2:$A$201,ROW()-4),"") | B15: =IF($A15="","",INDEX(Empleados!$E$2:$E$201,MATCH($A15,Empleados!$A$2:$A$201,0))) | C15: =IF($A15="","",INDEX(Empleados!$O$2:$O$201,MATCH($A15,Empleados!$A$2:$A$201,0))) | D15: =IF($A15="","",INDEX(Empleados!$P$2:$P$201,MATCH($A15,Empleados!$A$2:$A$201,0))) | E15: =IF($A15="","",IF($N15<>"ACTIVO",0,INDEX(Empleados!$M$2:$M$201,MATCH($A15,Empleados!$A$2:$A$201,0)))) | F15: =IF($A15="","",IF($N15<>"ACTIVO",0,INDEX(Empleados!$N$2:$N$201,MATCH($A15,Empleados!$A$2:$A$201,0)))) | G15: =IF($A15="","",IF($N15<>"ACTIVO",0,SUMIFS(Conceptos_Pago!$E$2:$E$100,Conceptos_Pago!$C$2:$C$100,"FIJO",Conceptos_Pago!$D$2:$D$100,"SI"))) | H15: =IF($A15="","",IF($N15<>"ACTIVO",0,SUMIFS(Movimientos!$F$2:$F$500,Movimientos!$A$2:$A$500,$B$2,Movimientos!$B$2:$B$500,$A15,Movimientos!$C$2:$C$500,"PAGO"))) | I15: =IF($A15="","",SUM(E15:H15)) | J15: =IF($A15="","",IF($N15<>"ACTIVO",0,SUMIFS(Deducciones!$E$2:$E$100,Deducciones!$F$2:$F$100,"SI",Deducciones!$G$2:$G$100,"SI",Deducciones!$C$2:$C$100,"FIJO")+E15*SUMIFS(Deducciones!$E$2:$E$100,Deducciones!$F$2:$F$100,"SI",Deducciones!$G$2:$G$100,"SI",Deducciones!$C$2:$C$100,"PORCENTAJE",Deducciones!$D$2:$D$100,"SUELDO_BASE")+I15*SUMIFS(Deducciones!$E$2:$E$100,Deducciones!$F$2:$F$100,"SI",Deducciones!$G$2:$G$100,"SI",Deducciones!$C$2:$C$100,"PORCENTAJE",Deducciones!$D$2:$D$100,"TOTAL_PERCEPCIONES"))) | K15: =IF($A15="","",IF($N15<>"ACTIVO",0,SUMIFS(Movimientos!$F$2:$F$500,Movimientos!$A$2:$A$500,$B$2,Movimientos!$B$2:$B$500,$A15,Movimientos!$C$2:$C$500,"DEDUCCION"))) | L15: =IF($A15="","",SUM(J15:K15)) | M15: =IF($A15="","",I15-L15) | N15: =IF($A15="","",INDEX(Empleados!$J$2:$J$201,MATCH($A15,Empleados!$A$2:$A$201,0)))
A16: =IF(ROW()-4<=COUNTA(Empleados!$A$2:$A$201),INDEX(Empleados!$A$2:$A$201,ROW()-4),"") | B16: =IF($A16="","",INDEX(Empleados!$E$2:$E$201,MATCH($A16,Empleados!$A$2:$A$201,0))) | C16: =IF($A16="","",INDEX(Empleados!$O$2:$O$201,MATCH($A16,Empleados!$A$2:$A$201,0))) | D16: =IF($A16="","",INDEX(Empleados!$P$2:$P$201,MATCH($A16,Empleados!$A$2:$A$201,0))) | E16: =IF($A16="","",IF($N16<>"ACTIVO",0,INDEX(Empleados!$M$2:$M$201,MATCH($A16,Empleados!$A$2:$A$201,0)))) | F16: =IF($A16="","",IF($N16<>"ACTIVO",0,INDEX(Empleados!$N$2:$N$201,MATCH($A16,Empleados!$A$2:$A$201,0)))) | G16: =IF($A16="","",IF($N16<>"ACTIVO",0,SUMIFS(Conceptos_Pago!$E$2:$E$100,Conceptos_Pago!$C$2:$C$100,"FIJO",Conceptos_Pago!$D$2:$D$100,"SI"))) | H16: =IF($A16="","",IF($N16<>"ACTIVO",0,SUMIFS(Movimientos!$F$2:$F$500,Movimientos!$A$2:$A$500,$B$2,Movimientos!$B$2:$B$500,$A16,Movimientos!$C$2:$C$500,"PAGO"))) | I16: =IF($A16="","",SUM(E16:H16)) | J16: =IF($A16="","",IF($N16<>"ACTIVO",0,SUMIFS(Deducciones!$E$2:$E$100,Deducciones!$F$2:$F$100,"SI",Deducciones!$G$2:$G$100,"SI",Deducciones!$C$2:$C$100,"FIJO")+E16*SUMIFS(Deducciones!$E$2:$E$100,Deducciones!$F$2:$F$100,"SI",Deducciones!$G$2:$G$100,"SI",Deducciones!$C$2:$C$100,"PORCENTAJE",Deducciones!$D$2:$D$100,"SUELDO_BASE")+I16*SUMIFS(Deducciones!$E$2:$E$100,Deducciones!$F$2:$F$100,"SI",Deducciones!$G$2:$G$100,"SI",Deducciones!$C$2:$C$100,"PORCENTAJE",Deducciones!$D$2:$D$100,"TOTAL_PERCEPCIONES"))) | K16: =IF($A16="","",IF($N16<>"ACTIVO",0,SUMIFS(Movimientos!$F$2:$F$500,Movimientos!$A$2:$A$500,$B$2,Movimientos!$B$2:$B$500,$A16,Movimientos!$C$2:$C$500,"DEDUCCION"))) | L16: =IF($A16="","",SUM(J16:K16)) | M16: =IF($A16="","",I16-L16) | N16: =IF($A16="","",INDEX(Empleados!$J$2:$J$201,MATCH($A16,Empleados!$A$2:$A$201,0)))
... A204: =IF(ROW()-4<=COUNTA(Empleados!$A$2:$A$201),INDEX(Empleados!$A$2:$A$201,ROW()-4),"") | B204: =IF($A204="","",INDEX(Empleados!$E$2:$E$201,MATCH($A204,Empleados!$A$2:$A$201,0))) | C204: =IF($A204="","",INDEX(Empleados!$O$2:$O$201,MATCH($A204,Empleados!$A$2:$A$201,0))) | D204: =IF($A204="","",INDEX(Empleados!$P$2:$P$201,MATCH($A204,Empleados!$A$2:$A$201,0))) | E204: =IF($A204="","",IF($N204<>"ACTIVO",0,INDEX(Empleados!$M$2:$M$201,MATCH($A204,Empleados!$A$2:$A$201,0)))) | F204: =IF($A204="","",IF($N204<>"ACTIVO",0,INDEX(Empleados!$N$2:$N$201,MATCH($A204,Empleados!$A$2:$A$201,0)))) | G204: =IF($A204="","",IF($N204<>"ACTIVO",0,SUMIFS(Conceptos_Pago!$E$2:$E$100,Conceptos_Pago!$C$2:$C$100,"FIJO",Conceptos_Pago!$D$2:$D$100,"SI"))) | H204: =IF($A204="","",IF($N204<>"ACTIVO",0,SUMIFS(Movimientos!$F$2:$F$500,Movimientos!$A$2:$A$500,$B$2,Movimientos!$B$2:$B$500,$A204,Movimientos!$C$2:$C$500,"PAGO"))) | I204: =IF($A204="","",SUM(E204:H204)) | J204: =IF($A204="","",IF($N204<>"ACTIVO",0,SUMIFS(Deducciones!$E$2:$E$100,Deducciones!$F$2:$F$100,"SI",Deducciones!$G$2:$G$100,"SI",Deducciones!$C$2:$C$100,"FIJO")+E204*SUMIFS(Deducciones!$E$2:$E$100,Deducciones!$F$2:$F$100,"SI",Deducciones!$G$2:$G$100,"SI",Deducciones!$C$2:$C$100,"PORCENTAJE",Deducciones!$D$2:$D$100,"SUELDO_BASE")+I204*SUMIFS(Deducciones!$E$2:$E$100,Deducciones!$F$2:$F$100,"SI",Deducciones!$G$2:$G$100,"SI",Deducciones!$C$2:$C$100,"PORCENTAJE",Deducciones!$D$2:$D$100,"TOTAL_PERCEPCIONES"))) | K204: =IF($A204="","",IF($N204<>"ACTIVO",0,SUMIFS(Movimientos!$F$2:$F$500,Movimientos!$A$2:$A$500,$B$2,Movimientos!$B$2:$B$500,$A204,Movimientos!$C$2:$C$500,"DEDUCCION"))) | L204: =IF($A204="","",SUM(J204:K204)) | M204: =IF($A204="","",I204-L204) | N204: =IF($A204="","",INDEX(Empleados!$J$2:$J$201,MATCH($A204,Empleados!$A$2:$A$201,0)))
A206: TOTALES | E206: =SUM(E5:E204) -> 58000 | F206: =SUM(F5:F204) -> 5500 | G206: =SUM(G5:G204) -> 4500 | H206: =SUM(H5:H204) -> 2220 | I206: =SUM(I5:I204) -> 70220 | J206: =SUM(J5:J204) -> 8472 | K206: =SUM(K5:K204) -> 900 | L206: =SUM(L5:L204) -> 9372 | M206: =SUM(M5:M204) -> 60848

Sheet usuarios
A1: username | B1: password_hash | C1: role | D1: curp | E1: rfc | F1: apellido_p | G1: apellido_m | H1: genero | I1: fecha_nacimiento | J1: calle | K1: numero | L1: colonia | M1: municipio | N1: estado | O1: telefono | P1: email
A2: admin | B2: $2a$10$0HDQKmHtj8WhnfN.0M/ADOe1ieBaeQfSWAAFbFaAtiYCCFGZRKEdS | C2: ADMIN
